LICENSE
MANIFEST.in
README.rst
requirements.txt
setup.cfg
setup.py
pwrcheck/__init__.py
pwrcheck/classes.py
pwrcheck/cmd.py
pwrcheck/constants.py
pwrcheck/exceptions.py
pwrcheck.egg-info/PKG-INFO
pwrcheck.egg-info/SOURCES.txt
pwrcheck.egg-info/dependency_links.txt
pwrcheck.egg-info/entry_points.txt
pwrcheck.egg-info/not-zip-safe
pwrcheck.egg-info/requires.txt
pwrcheck.egg-info/top_level.txt