Metadata-Version: 1.1
Name: pwrcheck
Version: 0.0.1b2
Summary: Python PWRCheck Reader.
Home-page: https://github.com/ampledata/pwrcheck
Author: Greg Albrecht
Author-email: oss@undef.net
License: Copyright 2018 Greg Albrecht
